pyamdgpuinfo/__init__.py
pyamdgpuinfo/_impl.cpython-311-x86_64-linux-musl.so
pyamdgpuinfo.libs/libdrm-f5f8fc5d.so.2.123.0
pyamdgpuinfo.libs/libdrm_amdgpu-550cc0eb.so.1.123.0
pyamdgpuinfo-2.1.7.dist-info/METADATA
pyamdgpuinfo-2.1.7.dist-info/WHEEL
pyamdgpuinfo-2.1.7.dist-info/top_level.txt
pyamdgpuinfo-2.1.7.dist-info/RECORD
pyamdgpuinfo-2.1.7.dist-info/licenses/LICENSE
