Metadata-Version: 2.4
Name: pyamdgpuinfo
Version: 2.1.7
Summary: AMD GPU stats
Home-page: https://github.com/mark9064/pyamdgpuinfo
Author: mark9064
Classifier: Programming Language :: Python :: 3
Classifier: Programming Language :: Cython
Classifier: License :: OSI Approved :: GNU General Public License v3 (GPLv3)
Classifier: Operating System :: POSIX :: Linux
Classifier: Development Status :: 5 - Production/Stable
Classifier: Natural Language :: English
Requires-Python: >=3.9
License-File: LICENSE
Dynamic: author
Dynamic: classifier
Dynamic: description
Dynamic: description-content-type
Dynamic: home-page
Dynamic: license-file
Dynamic: requires-python
Dynamic: summary
